ivis/__init__.py
ivis/ivis.py
ivis/version.py
ivis/data/__init__.py
ivis/data/data.py
ivis/data/generators/__init__.py
ivis/data/generators/generators.py
ivis/data/generators/triplet_generators.py
ivis/data/neighbour_retrieval/__init__.py
ivis/data/neighbour_retrieval/knn.py
ivis/data/neighbour_retrieval/supervised.py
ivis/data/sequence/__init__.py
ivis/data/sequence/image.py
ivis/data/sequence/sequence.py
ivis/nn/__init__.py
ivis/nn/callbacks.py
ivis/nn/distances.py
ivis/nn/losses.py
ivis/nn/network.py
ivis/utils/__init__.py
ivis/utils/deprecation.py
ivis/utils/vis_utils.py
ivis-2.0.11.dist-info/LICENSE
ivis-2.0.11.dist-info/METADATA
ivis-2.0.11.dist-info/WHEEL
ivis-2.0.11.dist-info/top_level.txt
ivis-2.0.11.dist-info/RECORD
