Metadata-Version: 2.1
Name: ivis
Version: 2.0.11
Summary: Artificial neural network-driven visualization of high-dimensional data using triplets.
Home-page: http://github.com/beringresearch/ivis
Author: Benjamin Szubert, Ignat Drozdov
Author-email: bszubert@beringresearch.com, idrozdov@beringresearch.com
License: Apache License, Version 2.0
Classifier: Programming Language :: Python :: 3
Classifier: Operating System :: OS Independent
Requires-Python: >=3.5
License-File: LICENSE
Requires-Dist: numpy
Requires-Dist: scikit-learn >0.20.0
Requires-Dist: annoy >=1.15.2
Requires-Dist: tqdm
Requires-Dist: dill
Provides-Extra: cpu
Requires-Dist: tensorflow-cpu <2.16,>=1.13.1 ; extra == 'cpu'
Provides-Extra: gpu
Requires-Dist: tensorflow <2.16,>=1.13.1 ; extra == 'gpu'
Provides-Extra: tests
Requires-Dist: pytest ; extra == 'tests'
Provides-Extra: visualization
Requires-Dist: matplotlib ; extra == 'visualization'
Requires-Dist: seaborn ; extra == 'visualization'
